{
  "kind": "pptx-png-theme-preview",
  "source": "examples/theme-preview-en/deck.md",
  "generatedAt": "source-controlled",
  "pngSize": {
    "width": 1600,
    "height": 900
  },
  "styleCount": 8,
  "styleNames": [
    "clean",
    "data",
    "editorial",
    "glass",
    "grid",
    "magazine",
    "minimalism",
    "newmorphism"
  ],
  "slideCount": 24,
  "compositionClasses": [
    "chart-table",
    "comparison",
    "cover",
    "grid",
    "image-focus",
    "key-message",
    "pipeline",
    "table-focus",
    "timeline",
    "toc",
    "vertical-list"
  ],
  "surfaceVariants": [
    "flag-drop",
    "notched-corner",
    "rounded",
    "ticket",
    "two-corner-left",
    "two-corner-right"
  ],
  "proofKinds": [
    "arc-ring",
    "bar",
    "connected-strip",
    "gauge"
  ],
  "themes": [
    {
      "name": "clean",
      "pptx": "pptx/clean.pptx",
      "slides": [
        {
          "index": 1,
          "file": "slides/clean/slide-01.png",
          "title": "MDPR Design Grammar",
          "composition": "cover"
        },
        {
          "index": 2,
          "file": "slides/clean/slide-02.png",
          "title": "Agenda",
          "composition": "toc"
        },
        {
          "index": 3,
          "file": "slides/clean/slide-03.png",
          "title": "Agenda (Cont. 2/2)",
          "composition": "toc"
        },
        {
          "index": 4,
          "file": "slides/clean/slide-04.png",
          "title": "Teaser Summary",
          "composition": "key-message"
        },
        {
          "index": 5,
          "file": "slides/clean/slide-05.png",
          "title": "Composition Contract",
          "composition": "vertical-list"
        },
        {
          "index": 6,
          "file": "slides/clean/slide-06.png",
          "title": "Composition Contract (Cont. 2/2)",
          "composition": "comparison"
        },
        {
          "index": 7,
          "file": "slides/clean/slide-07.png",
          "title": "Pruned Style Families",
          "composition": "vertical-list"
        },
        {
          "index": 8,
          "file": "slides/clean/slide-08.png",
          "title": "Pruned Style Families (Cont. 2/2)",
          "composition": "comparison"
        },
        {
          "index": 9,
          "file": "slides/clean/slide-09.png",
          "title": "Semantic Blocks",
          "composition": "grid"
        },
        {
          "index": 10,
          "file": "slides/clean/slide-10.png",
          "title": "Pipeline Diagram",
          "composition": "pipeline"
        },
        {
          "index": 11,
          "file": "slides/clean/slide-11.png",
          "title": "Decoration Pattern Catalog",
          "composition": "timeline"
        },
        {
          "index": 12,
          "file": "slides/clean/slide-12.png",
          "title": "Decoration Pattern Catalog (Cont. 2/2)",
          "composition": "comparison"
        },
        {
          "index": 13,
          "file": "slides/clean/slide-13.png",
          "title": "Table Coherence",
          "composition": "table-focus"
        },
        {
          "index": 14,
          "file": "slides/clean/slide-14.png",
          "title": "Chart and Table Pair",
          "composition": "chart-table"
        },
        {
          "index": 15,
          "file": "slides/clean/slide-15.png",
          "title": "Chart and Table Pair (Cont. 2/2)",
          "composition": "table-focus"
        },
        {
          "index": 16,
          "file": "slides/clean/slide-16.png",
          "title": "Editable Proof Objects",
          "composition": "chart-table"
        },
        {
          "index": 17,
          "file": "slides/clean/slide-17.png",
          "title": "Editable Proof Objects (Cont. 2/2)",
          "composition": "chart-table"
        },
        {
          "index": 18,
          "file": "slides/clean/slide-18.png",
          "title": "Object Shape Grammar",
          "composition": "timeline"
        },
        {
          "index": 19,
          "file": "slides/clean/slide-19.png",
          "title": "Object Shape Grammar (Cont. 2/2)",
          "composition": "comparison"
        },
        {
          "index": 20,
          "file": "slides/clean/slide-20.png",
          "title": "Icon and Text Aside",
          "composition": "grid"
        },
        {
          "index": 21,
          "file": "slides/clean/slide-21.png",
          "title": "Overflow Guard",
          "composition": "grid"
        },
        {
          "index": 22,
          "file": "slides/clean/slide-22.png",
          "title": "Image Safe Frame",
          "composition": "image-focus"
        },
        {
          "index": 23,
          "file": "slides/clean/slide-23.png",
          "title": "Mixed Object Packing",
          "composition": "chart-table"
        },
        {
          "index": 24,
          "file": "slides/clean/slide-24.png",
          "title": "Actions Output Review",
          "composition": "vertical-list"
        }
      ],
      "colors": {
        "background": "#F8FAFC",
        "text": "#111827",
        "primary": "#2563EB",
        "secondary": "#DBEAFE",
        "surface": "#FFFFFF"
      }
    },
    {
      "name": "editorial",
      "pptx": "pptx/editorial.pptx",
      "slides": [
        {
          "index": 1,
          "file": "slides/editorial/slide-01.png",
          "title": "MDPR Design Grammar",
          "composition": "cover"
        },
        {
          "index": 2,
          "file": "slides/editorial/slide-02.png",
          "title": "Agenda",
          "composition": "toc"
        },
        {
          "index": 3,
          "file": "slides/editorial/slide-03.png",
          "title": "Agenda (Cont. 2/2)",
          "composition": "toc"
        },
        {
          "index": 4,
          "file": "slides/editorial/slide-04.png",
          "title": "Teaser Summary",
          "composition": "key-message"
        },
        {
          "index": 5,
          "file": "slides/editorial/slide-05.png",
          "title": "Composition Contract",
          "composition": "vertical-list"
        },
        {
          "index": 6,
          "file": "slides/editorial/slide-06.png",
          "title": "Composition Contract (Cont. 2/2)",
          "composition": "comparison"
        },
        {
          "index": 7,
          "file": "slides/editorial/slide-07.png",
          "title": "Pruned Style Families",
          "composition": "vertical-list"
        },
        {
          "index": 8,
          "file": "slides/editorial/slide-08.png",
          "title": "Pruned Style Families (Cont. 2/2)",
          "composition": "comparison"
        },
        {
          "index": 9,
          "file": "slides/editorial/slide-09.png",
          "title": "Semantic Blocks",
          "composition": "grid"
        },
        {
          "index": 10,
          "file": "slides/editorial/slide-10.png",
          "title": "Pipeline Diagram",
          "composition": "pipeline"
        },
        {
          "index": 11,
          "file": "slides/editorial/slide-11.png",
          "title": "Decoration Pattern Catalog",
          "composition": "timeline"
        },
        {
          "index": 12,
          "file": "slides/editorial/slide-12.png",
          "title": "Decoration Pattern Catalog (Cont. 2/2)",
          "composition": "comparison"
        },
        {
          "index": 13,
          "file": "slides/editorial/slide-13.png",
          "title": "Table Coherence",
          "composition": "table-focus"
        },
        {
          "index": 14,
          "file": "slides/editorial/slide-14.png",
          "title": "Chart and Table Pair",
          "composition": "chart-table"
        },
        {
          "index": 15,
          "file": "slides/editorial/slide-15.png",
          "title": "Chart and Table Pair (Cont. 2/2)",
          "composition": "table-focus"
        },
        {
          "index": 16,
          "file": "slides/editorial/slide-16.png",
          "title": "Editable Proof Objects",
          "composition": "chart-table"
        },
        {
          "index": 17,
          "file": "slides/editorial/slide-17.png",
          "title": "Editable Proof Objects (Cont. 2/2)",
          "composition": "chart-table"
        },
        {
          "index": 18,
          "file": "slides/editorial/slide-18.png",
          "title": "Object Shape Grammar",
          "composition": "timeline"
        },
        {
          "index": 19,
          "file": "slides/editorial/slide-19.png",
          "title": "Object Shape Grammar (Cont. 2/2)",
          "composition": "comparison"
        },
        {
          "index": 20,
          "file": "slides/editorial/slide-20.png",
          "title": "Icon and Text Aside",
          "composition": "grid"
        },
        {
          "index": 21,
          "file": "slides/editorial/slide-21.png",
          "title": "Overflow Guard",
          "composition": "grid"
        },
        {
          "index": 22,
          "file": "slides/editorial/slide-22.png",
          "title": "Image Safe Frame",
          "composition": "image-focus"
        },
        {
          "index": 23,
          "file": "slides/editorial/slide-23.png",
          "title": "Mixed Object Packing",
          "composition": "chart-table"
        },
        {
          "index": 24,
          "file": "slides/editorial/slide-24.png",
          "title": "Actions Output Review",
          "composition": "vertical-list"
        }
      ],
      "colors": {
        "background": "#F7F3EF",
        "text": "#1F2937",
        "primary": "#B45309",
        "secondary": "#FCD34D",
        "surface": "#FFFBF5"
      }
    },
    {
      "name": "minimalism",
      "pptx": "pptx/minimalism.pptx",
      "slides": [
        {
          "index": 1,
          "file": "slides/minimalism/slide-01.png",
          "title": "MDPR Design Grammar",
          "composition": "cover"
        },
        {
          "index": 2,
          "file": "slides/minimalism/slide-02.png",
          "title": "Agenda",
          "composition": "toc"
        },
        {
          "index": 3,
          "file": "slides/minimalism/slide-03.png",
          "title": "Agenda (Cont. 2/2)",
          "composition": "toc"
        },
        {
          "index": 4,
          "file": "slides/minimalism/slide-04.png",
          "title": "Teaser Summary",
          "composition": "key-message"
        },
        {
          "index": 5,
          "file": "slides/minimalism/slide-05.png",
          "title": "Composition Contract",
          "composition": "vertical-list"
        },
        {
          "index": 6,
          "file": "slides/minimalism/slide-06.png",
          "title": "Composition Contract (Cont. 2/2)",
          "composition": "comparison"
        },
        {
          "index": 7,
          "file": "slides/minimalism/slide-07.png",
          "title": "Pruned Style Families",
          "composition": "vertical-list"
        },
        {
          "index": 8,
          "file": "slides/minimalism/slide-08.png",
          "title": "Pruned Style Families (Cont. 2/2)",
          "composition": "comparison"
        },
        {
          "index": 9,
          "file": "slides/minimalism/slide-09.png",
          "title": "Semantic Blocks",
          "composition": "grid"
        },
        {
          "index": 10,
          "file": "slides/minimalism/slide-10.png",
          "title": "Pipeline Diagram",
          "composition": "pipeline"
        },
        {
          "index": 11,
          "file": "slides/minimalism/slide-11.png",
          "title": "Decoration Pattern Catalog",
          "composition": "timeline"
        },
        {
          "index": 12,
          "file": "slides/minimalism/slide-12.png",
          "title": "Decoration Pattern Catalog (Cont. 2/2)",
          "composition": "comparison"
        },
        {
          "index": 13,
          "file": "slides/minimalism/slide-13.png",
          "title": "Table Coherence",
          "composition": "table-focus"
        },
        {
          "index": 14,
          "file": "slides/minimalism/slide-14.png",
          "title": "Chart and Table Pair",
          "composition": "chart-table"
        },
        {
          "index": 15,
          "file": "slides/minimalism/slide-15.png",
          "title": "Chart and Table Pair (Cont. 2/2)",
          "composition": "table-focus"
        },
        {
          "index": 16,
          "file": "slides/minimalism/slide-16.png",
          "title": "Editable Proof Objects",
          "composition": "chart-table"
        },
        {
          "index": 17,
          "file": "slides/minimalism/slide-17.png",
          "title": "Editable Proof Objects (Cont. 2/2)",
          "composition": "chart-table"
        },
        {
          "index": 18,
          "file": "slides/minimalism/slide-18.png",
          "title": "Object Shape Grammar",
          "composition": "timeline"
        },
        {
          "index": 19,
          "file": "slides/minimalism/slide-19.png",
          "title": "Object Shape Grammar (Cont. 2/2)",
          "composition": "comparison"
        },
        {
          "index": 20,
          "file": "slides/minimalism/slide-20.png",
          "title": "Icon and Text Aside",
          "composition": "grid"
        },
        {
          "index": 21,
          "file": "slides/minimalism/slide-21.png",
          "title": "Overflow Guard",
          "composition": "grid"
        },
        {
          "index": 22,
          "file": "slides/minimalism/slide-22.png",
          "title": "Image Safe Frame",
          "composition": "image-focus"
        },
        {
          "index": 23,
          "file": "slides/minimalism/slide-23.png",
          "title": "Mixed Object Packing",
          "composition": "chart-table"
        },
        {
          "index": 24,
          "file": "slides/minimalism/slide-24.png",
          "title": "Actions Output Review",
          "composition": "vertical-list"
        }
      ],
      "colors": {
        "background": "#FFFFFF",
        "text": "#111827",
        "primary": "#111827",
        "secondary": "#E5E7EB",
        "surface": "#FFFFFF"
      }
    },
    {
      "name": "newmorphism",
      "pptx": "pptx/newmorphism.pptx",
      "slides": [
        {
          "index": 1,
          "file": "slides/newmorphism/slide-01.png",
          "title": "MDPR Design Grammar",
          "composition": "cover"
        },
        {
          "index": 2,
          "file": "slides/newmorphism/slide-02.png",
          "title": "Agenda",
          "composition": "toc"
        },
        {
          "index": 3,
          "file": "slides/newmorphism/slide-03.png",
          "title": "Agenda (Cont. 2/2)",
          "composition": "toc"
        },
        {
          "index": 4,
          "file": "slides/newmorphism/slide-04.png",
          "title": "Teaser Summary",
          "composition": "key-message"
        },
        {
          "index": 5,
          "file": "slides/newmorphism/slide-05.png",
          "title": "Composition Contract",
          "composition": "vertical-list"
        },
        {
          "index": 6,
          "file": "slides/newmorphism/slide-06.png",
          "title": "Composition Contract (Cont. 2/2)",
          "composition": "comparison"
        },
        {
          "index": 7,
          "file": "slides/newmorphism/slide-07.png",
          "title": "Pruned Style Families",
          "composition": "vertical-list"
        },
        {
          "index": 8,
          "file": "slides/newmorphism/slide-08.png",
          "title": "Pruned Style Families (Cont. 2/2)",
          "composition": "comparison"
        },
        {
          "index": 9,
          "file": "slides/newmorphism/slide-09.png",
          "title": "Semantic Blocks",
          "composition": "grid"
        },
        {
          "index": 10,
          "file": "slides/newmorphism/slide-10.png",
          "title": "Pipeline Diagram",
          "composition": "pipeline"
        },
        {
          "index": 11,
          "file": "slides/newmorphism/slide-11.png",
          "title": "Decoration Pattern Catalog",
          "composition": "timeline"
        },
        {
          "index": 12,
          "file": "slides/newmorphism/slide-12.png",
          "title": "Decoration Pattern Catalog (Cont. 2/2)",
          "composition": "comparison"
        },
        {
          "index": 13,
          "file": "slides/newmorphism/slide-13.png",
          "title": "Table Coherence",
          "composition": "table-focus"
        },
        {
          "index": 14,
          "file": "slides/newmorphism/slide-14.png",
          "title": "Chart and Table Pair",
          "composition": "chart-table"
        },
        {
          "index": 15,
          "file": "slides/newmorphism/slide-15.png",
          "title": "Chart and Table Pair (Cont. 2/2)",
          "composition": "table-focus"
        },
        {
          "index": 16,
          "file": "slides/newmorphism/slide-16.png",
          "title": "Editable Proof Objects",
          "composition": "chart-table"
        },
        {
          "index": 17,
          "file": "slides/newmorphism/slide-17.png",
          "title": "Editable Proof Objects (Cont. 2/2)",
          "composition": "chart-table"
        },
        {
          "index": 18,
          "file": "slides/newmorphism/slide-18.png",
          "title": "Object Shape Grammar",
          "composition": "timeline"
        },
        {
          "index": 19,
          "file": "slides/newmorphism/slide-19.png",
          "title": "Object Shape Grammar (Cont. 2/2)",
          "composition": "comparison"
        },
        {
          "index": 20,
          "file": "slides/newmorphism/slide-20.png",
          "title": "Icon and Text Aside",
          "composition": "grid"
        },
        {
          "index": 21,
          "file": "slides/newmorphism/slide-21.png",
          "title": "Overflow Guard",
          "composition": "grid"
        },
        {
          "index": 22,
          "file": "slides/newmorphism/slide-22.png",
          "title": "Image Safe Frame",
          "composition": "image-focus"
        },
        {
          "index": 23,
          "file": "slides/newmorphism/slide-23.png",
          "title": "Mixed Object Packing",
          "composition": "chart-table"
        },
        {
          "index": 24,
          "file": "slides/newmorphism/slide-24.png",
          "title": "Actions Output Review",
          "composition": "vertical-list"
        }
      ],
      "colors": {
        "background": "#E9EEF5",
        "text": "#243041",
        "primary": "#4F6F8F",
        "secondary": "#CBD5E1",
        "surface": "#E9EEF5"
      }
    },
    {
      "name": "glass",
      "pptx": "pptx/glass.pptx",
      "slides": [
        {
          "index": 1,
          "file": "slides/glass/slide-01.png",
          "title": "MDPR Design Grammar",
          "composition": "cover"
        },
        {
          "index": 2,
          "file": "slides/glass/slide-02.png",
          "title": "Agenda",
          "composition": "toc"
        },
        {
          "index": 3,
          "file": "slides/glass/slide-03.png",
          "title": "Agenda (Cont. 2/2)",
          "composition": "toc"
        },
        {
          "index": 4,
          "file": "slides/glass/slide-04.png",
          "title": "Teaser Summary",
          "composition": "key-message"
        },
        {
          "index": 5,
          "file": "slides/glass/slide-05.png",
          "title": "Composition Contract",
          "composition": "vertical-list"
        },
        {
          "index": 6,
          "file": "slides/glass/slide-06.png",
          "title": "Composition Contract (Cont. 2/2)",
          "composition": "comparison"
        },
        {
          "index": 7,
          "file": "slides/glass/slide-07.png",
          "title": "Pruned Style Families",
          "composition": "vertical-list"
        },
        {
          "index": 8,
          "file": "slides/glass/slide-08.png",
          "title": "Pruned Style Families (Cont. 2/2)",
          "composition": "comparison"
        },
        {
          "index": 9,
          "file": "slides/glass/slide-09.png",
          "title": "Semantic Blocks",
          "composition": "grid"
        },
        {
          "index": 10,
          "file": "slides/glass/slide-10.png",
          "title": "Pipeline Diagram",
          "composition": "pipeline"
        },
        {
          "index": 11,
          "file": "slides/glass/slide-11.png",
          "title": "Decoration Pattern Catalog",
          "composition": "timeline"
        },
        {
          "index": 12,
          "file": "slides/glass/slide-12.png",
          "title": "Decoration Pattern Catalog (Cont. 2/2)",
          "composition": "comparison"
        },
        {
          "index": 13,
          "file": "slides/glass/slide-13.png",
          "title": "Table Coherence",
          "composition": "table-focus"
        },
        {
          "index": 14,
          "file": "slides/glass/slide-14.png",
          "title": "Chart and Table Pair",
          "composition": "chart-table"
        },
        {
          "index": 15,
          "file": "slides/glass/slide-15.png",
          "title": "Chart and Table Pair (Cont. 2/2)",
          "composition": "table-focus"
        },
        {
          "index": 16,
          "file": "slides/glass/slide-16.png",
          "title": "Editable Proof Objects",
          "composition": "chart-table"
        },
        {
          "index": 17,
          "file": "slides/glass/slide-17.png",
          "title": "Editable Proof Objects (Cont. 2/2)",
          "composition": "chart-table"
        },
        {
          "index": 18,
          "file": "slides/glass/slide-18.png",
          "title": "Object Shape Grammar",
          "composition": "timeline"
        },
        {
          "index": 19,
          "file": "slides/glass/slide-19.png",
          "title": "Object Shape Grammar (Cont. 2/2)",
          "composition": "comparison"
        },
        {
          "index": 20,
          "file": "slides/glass/slide-20.png",
          "title": "Icon and Text Aside",
          "composition": "grid"
        },
        {
          "index": 21,
          "file": "slides/glass/slide-21.png",
          "title": "Overflow Guard",
          "composition": "grid"
        },
        {
          "index": 22,
          "file": "slides/glass/slide-22.png",
          "title": "Image Safe Frame",
          "composition": "image-focus"
        },
        {
          "index": 23,
          "file": "slides/glass/slide-23.png",
          "title": "Mixed Object Packing",
          "composition": "chart-table"
        },
        {
          "index": 24,
          "file": "slides/glass/slide-24.png",
          "title": "Actions Output Review",
          "composition": "vertical-list"
        }
      ],
      "colors": {
        "background": "#0B1020",
        "text": "#F8FAFC",
        "primary": "#8A4FFF",
        "secondary": "#22D3EE",
        "surface": "#17213A"
      }
    },
    {
      "name": "grid",
      "pptx": "pptx/grid.pptx",
      "slides": [
        {
          "index": 1,
          "file": "slides/grid/slide-01.png",
          "title": "MDPR Design Grammar",
          "composition": "cover"
        },
        {
          "index": 2,
          "file": "slides/grid/slide-02.png",
          "title": "Agenda",
          "composition": "toc"
        },
        {
          "index": 3,
          "file": "slides/grid/slide-03.png",
          "title": "Agenda (Cont. 2/2)",
          "composition": "toc"
        },
        {
          "index": 4,
          "file": "slides/grid/slide-04.png",
          "title": "Teaser Summary",
          "composition": "key-message"
        },
        {
          "index": 5,
          "file": "slides/grid/slide-05.png",
          "title": "Composition Contract",
          "composition": "vertical-list"
        },
        {
          "index": 6,
          "file": "slides/grid/slide-06.png",
          "title": "Composition Contract (Cont. 2/2)",
          "composition": "comparison"
        },
        {
          "index": 7,
          "file": "slides/grid/slide-07.png",
          "title": "Pruned Style Families",
          "composition": "vertical-list"
        },
        {
          "index": 8,
          "file": "slides/grid/slide-08.png",
          "title": "Pruned Style Families (Cont. 2/2)",
          "composition": "comparison"
        },
        {
          "index": 9,
          "file": "slides/grid/slide-09.png",
          "title": "Semantic Blocks",
          "composition": "grid"
        },
        {
          "index": 10,
          "file": "slides/grid/slide-10.png",
          "title": "Pipeline Diagram",
          "composition": "pipeline"
        },
        {
          "index": 11,
          "file": "slides/grid/slide-11.png",
          "title": "Decoration Pattern Catalog",
          "composition": "timeline"
        },
        {
          "index": 12,
          "file": "slides/grid/slide-12.png",
          "title": "Decoration Pattern Catalog (Cont. 2/2)",
          "composition": "comparison"
        },
        {
          "index": 13,
          "file": "slides/grid/slide-13.png",
          "title": "Table Coherence",
          "composition": "table-focus"
        },
        {
          "index": 14,
          "file": "slides/grid/slide-14.png",
          "title": "Chart and Table Pair",
          "composition": "chart-table"
        },
        {
          "index": 15,
          "file": "slides/grid/slide-15.png",
          "title": "Chart and Table Pair (Cont. 2/2)",
          "composition": "table-focus"
        },
        {
          "index": 16,
          "file": "slides/grid/slide-16.png",
          "title": "Editable Proof Objects",
          "composition": "chart-table"
        },
        {
          "index": 17,
          "file": "slides/grid/slide-17.png",
          "title": "Editable Proof Objects (Cont. 2/2)",
          "composition": "chart-table"
        },
        {
          "index": 18,
          "file": "slides/grid/slide-18.png",
          "title": "Object Shape Grammar",
          "composition": "timeline"
        },
        {
          "index": 19,
          "file": "slides/grid/slide-19.png",
          "title": "Object Shape Grammar (Cont. 2/2)",
          "composition": "comparison"
        },
        {
          "index": 20,
          "file": "slides/grid/slide-20.png",
          "title": "Icon and Text Aside",
          "composition": "grid"
        },
        {
          "index": 21,
          "file": "slides/grid/slide-21.png",
          "title": "Overflow Guard",
          "composition": "grid"
        },
        {
          "index": 22,
          "file": "slides/grid/slide-22.png",
          "title": "Image Safe Frame",
          "composition": "image-focus"
        },
        {
          "index": 23,
          "file": "slides/grid/slide-23.png",
          "title": "Mixed Object Packing",
          "composition": "chart-table"
        },
        {
          "index": 24,
          "file": "slides/grid/slide-24.png",
          "title": "Actions Output Review",
          "composition": "vertical-list"
        }
      ],
      "colors": {
        "background": "#F8FAFC",
        "text": "#111827",
        "primary": "#DC2626",
        "secondary": "#111827",
        "surface": "#FFFFFF"
      }
    },
    {
      "name": "data",
      "pptx": "pptx/data.pptx",
      "slides": [
        {
          "index": 1,
          "file": "slides/data/slide-01.png",
          "title": "MDPR Design Grammar",
          "composition": "cover"
        },
        {
          "index": 2,
          "file": "slides/data/slide-02.png",
          "title": "Agenda",
          "composition": "toc"
        },
        {
          "index": 3,
          "file": "slides/data/slide-03.png",
          "title": "Agenda (Cont. 2/2)",
          "composition": "toc"
        },
        {
          "index": 4,
          "file": "slides/data/slide-04.png",
          "title": "Teaser Summary",
          "composition": "key-message"
        },
        {
          "index": 5,
          "file": "slides/data/slide-05.png",
          "title": "Composition Contract",
          "composition": "vertical-list"
        },
        {
          "index": 6,
          "file": "slides/data/slide-06.png",
          "title": "Composition Contract (Cont. 2/2)",
          "composition": "comparison"
        },
        {
          "index": 7,
          "file": "slides/data/slide-07.png",
          "title": "Pruned Style Families",
          "composition": "vertical-list"
        },
        {
          "index": 8,
          "file": "slides/data/slide-08.png",
          "title": "Pruned Style Families (Cont. 2/2)",
          "composition": "comparison"
        },
        {
          "index": 9,
          "file": "slides/data/slide-09.png",
          "title": "Semantic Blocks",
          "composition": "grid"
        },
        {
          "index": 10,
          "file": "slides/data/slide-10.png",
          "title": "Pipeline Diagram",
          "composition": "pipeline"
        },
        {
          "index": 11,
          "file": "slides/data/slide-11.png",
          "title": "Decoration Pattern Catalog",
          "composition": "timeline"
        },
        {
          "index": 12,
          "file": "slides/data/slide-12.png",
          "title": "Decoration Pattern Catalog (Cont. 2/2)",
          "composition": "comparison"
        },
        {
          "index": 13,
          "file": "slides/data/slide-13.png",
          "title": "Table Coherence",
          "composition": "table-focus"
        },
        {
          "index": 14,
          "file": "slides/data/slide-14.png",
          "title": "Chart and Table Pair",
          "composition": "chart-table"
        },
        {
          "index": 15,
          "file": "slides/data/slide-15.png",
          "title": "Chart and Table Pair (Cont. 2/2)",
          "composition": "table-focus"
        },
        {
          "index": 16,
          "file": "slides/data/slide-16.png",
          "title": "Editable Proof Objects",
          "composition": "chart-table"
        },
        {
          "index": 17,
          "file": "slides/data/slide-17.png",
          "title": "Editable Proof Objects (Cont. 2/2)",
          "composition": "chart-table"
        },
        {
          "index": 18,
          "file": "slides/data/slide-18.png",
          "title": "Object Shape Grammar",
          "composition": "timeline"
        },
        {
          "index": 19,
          "file": "slides/data/slide-19.png",
          "title": "Object Shape Grammar (Cont. 2/2)",
          "composition": "comparison"
        },
        {
          "index": 20,
          "file": "slides/data/slide-20.png",
          "title": "Icon and Text Aside",
          "composition": "grid"
        },
        {
          "index": 21,
          "file": "slides/data/slide-21.png",
          "title": "Overflow Guard",
          "composition": "grid"
        },
        {
          "index": 22,
          "file": "slides/data/slide-22.png",
          "title": "Image Safe Frame",
          "composition": "image-focus"
        },
        {
          "index": 23,
          "file": "slides/data/slide-23.png",
          "title": "Mixed Object Packing",
          "composition": "chart-table"
        },
        {
          "index": 24,
          "file": "slides/data/slide-24.png",
          "title": "Actions Output Review",
          "composition": "vertical-list"
        }
      ],
      "colors": {
        "background": "#101820",
        "text": "#F8FAFC",
        "primary": "#F59E0B",
        "secondary": "#38BDF8",
        "surface": "#162331"
      }
    },
    {
      "name": "magazine",
      "pptx": "pptx/magazine.pptx",
      "slides": [
        {
          "index": 1,
          "file": "slides/magazine/slide-01.png",
          "title": "MDPR Design Grammar",
          "composition": "cover"
        },
        {
          "index": 2,
          "file": "slides/magazine/slide-02.png",
          "title": "Agenda",
          "composition": "toc"
        },
        {
          "index": 3,
          "file": "slides/magazine/slide-03.png",
          "title": "Agenda (Cont. 2/2)",
          "composition": "toc"
        },
        {
          "index": 4,
          "file": "slides/magazine/slide-04.png",
          "title": "Teaser Summary",
          "composition": "key-message"
        },
        {
          "index": 5,
          "file": "slides/magazine/slide-05.png",
          "title": "Composition Contract",
          "composition": "vertical-list"
        },
        {
          "index": 6,
          "file": "slides/magazine/slide-06.png",
          "title": "Composition Contract (Cont. 2/2)",
          "composition": "comparison"
        },
        {
          "index": 7,
          "file": "slides/magazine/slide-07.png",
          "title": "Pruned Style Families",
          "composition": "vertical-list"
        },
        {
          "index": 8,
          "file": "slides/magazine/slide-08.png",
          "title": "Pruned Style Families (Cont. 2/2)",
          "composition": "comparison"
        },
        {
          "index": 9,
          "file": "slides/magazine/slide-09.png",
          "title": "Semantic Blocks",
          "composition": "grid"
        },
        {
          "index": 10,
          "file": "slides/magazine/slide-10.png",
          "title": "Pipeline Diagram",
          "composition": "pipeline"
        },
        {
          "index": 11,
          "file": "slides/magazine/slide-11.png",
          "title": "Decoration Pattern Catalog",
          "composition": "timeline"
        },
        {
          "index": 12,
          "file": "slides/magazine/slide-12.png",
          "title": "Decoration Pattern Catalog (Cont. 2/2)",
          "composition": "comparison"
        },
        {
          "index": 13,
          "file": "slides/magazine/slide-13.png",
          "title": "Table Coherence",
          "composition": "table-focus"
        },
        {
          "index": 14,
          "file": "slides/magazine/slide-14.png",
          "title": "Chart and Table Pair",
          "composition": "chart-table"
        },
        {
          "index": 15,
          "file": "slides/magazine/slide-15.png",
          "title": "Chart and Table Pair (Cont. 2/2)",
          "composition": "table-focus"
        },
        {
          "index": 16,
          "file": "slides/magazine/slide-16.png",
          "title": "Editable Proof Objects",
          "composition": "chart-table"
        },
        {
          "index": 17,
          "file": "slides/magazine/slide-17.png",
          "title": "Editable Proof Objects (Cont. 2/2)",
          "composition": "chart-table"
        },
        {
          "index": 18,
          "file": "slides/magazine/slide-18.png",
          "title": "Object Shape Grammar",
          "composition": "timeline"
        },
        {
          "index": 19,
          "file": "slides/magazine/slide-19.png",
          "title": "Object Shape Grammar (Cont. 2/2)",
          "composition": "comparison"
        },
        {
          "index": 20,
          "file": "slides/magazine/slide-20.png",
          "title": "Icon and Text Aside",
          "composition": "grid"
        },
        {
          "index": 21,
          "file": "slides/magazine/slide-21.png",
          "title": "Overflow Guard",
          "composition": "grid"
        },
        {
          "index": 22,
          "file": "slides/magazine/slide-22.png",
          "title": "Image Safe Frame",
          "composition": "image-focus"
        },
        {
          "index": 23,
          "file": "slides/magazine/slide-23.png",
          "title": "Mixed Object Packing",
          "composition": "chart-table"
        },
        {
          "index": 24,
          "file": "slides/magazine/slide-24.png",
          "title": "Actions Output Review",
          "composition": "vertical-list"
        }
      ],
      "colors": {
        "background": "#F8F4EF",
        "text": "#18181B",
        "primary": "#C2410C",
        "secondary": "#111827",
        "surface": "#FFFCF7"
      }
    }
  ]
}
